django_push_notifications_rubgomez93-1.6.3.dist-info/METADATA
django_push_notifications_rubgomez93-1.6.3.dist-info/RECORD
django_push_notifications_rubgomez93-1.6.3.dist-info/WHEEL
django_push_notifications_rubgomez93-1.6.3.dist-info/top_level.txt
push_notifications/__init__.py
push_notifications/admin.py
push_notifications/apns.py
push_notifications/apns_errors.py
push_notifications/fields.py
push_notifications/gcm.py
push_notifications/models.py
push_notifications/settings.py
push_notifications/webpush.py
push_notifications/wns.py
push_notifications/api/__init__.py
push_notifications/api/rest_framework.py
push_notifications/conf/__init__.py
push_notifications/conf/app.py
push_notifications/conf/appmodel.py
push_notifications/conf/base.py
push_notifications/conf/legacy.py
push_notifications/migrations/0001_initial.py
push_notifications/migrations/0002_auto_20160106_0850.py
push_notifications/migrations/0003_wnsdevice.py
push_notifications/migrations/0004_fcm.py
push_notifications/migrations/0005_applicationid.py
push_notifications/migrations/0006_webpushdevice.py
push_notifications/migrations/0007_auto_20180615_1226.py
push_notifications/migrations/__init__.py
